pysmelt-0.10.1.dist-info/METADATA
pysmelt-0.10.1.dist-info/WHEEL
pysmelt-0.10.1.dist-info/entry_points.txt
pysmelt/__init__.py
pysmelt/class_utils.py
pysmelt/cli.py
pysmelt/command.status
pysmelt/default_targets.py
pysmelt/generators/procedural.py
pysmelt/importer.py
pysmelt/interfaces/__init__.py
pysmelt/interfaces/analysis.py
pysmelt/interfaces/command.py
pysmelt/interfaces/converter.py
pysmelt/interfaces/executed_tests.py
pysmelt/interfaces/paths.py
pysmelt/interfaces/procedural.py
pysmelt/interfaces/runtime.py
pysmelt/interfaces/target.py
pysmelt/output.py
pysmelt/output_utils.py
pysmelt/path_utils.py
pysmelt/proto/__init__.py
pysmelt/proto/executed_tests/__init__.py
pysmelt/proto/smelt_client/__init__.py
pysmelt/proto/smelt_client/commands/__init__.py
pysmelt/proto/smelt_telemetry/__init__.py
pysmelt/pygraph.py
pysmelt/pysmelt.cpython-39-darwin.so
pysmelt/rc.py
pysmelt/serde.py
pysmelt/smelt_muncher.py
pysmelt/subscribers/__init__.py
pysmelt/subscribers/error_handler.py
pysmelt/subscribers/invocation_builder.py
pysmelt/subscribers/is_done.py
pysmelt/subscribers/output_collector.py
pysmelt/subscribers/retcode.py
pysmelt/subscribers/simple_profiler.py
pysmelt/subscribers/stdout.py
pysmelt/target.py
pysmelt/templates/__init__.py
pysmelt/templates/template_rule.py
pysmelt/tracker.py
pysmelt-0.10.1.dist-info/RECORD
