Metadata-Version: 2.4
Name: pysmelt
Version: 0.10.1
Requires-Dist: typer>=0.9.0
Requires-Dist: pyyaml>=6.0.1
Requires-Dist: pydantic>=2.6.0
Requires-Dist: toml>=0.10.2
Requires-Dist: betterproto[compiler]==2.0.0b6
Requires-Dist: rich>=13.7.1
Requires-Dist: junitparser>=3.1.2
Summary: smelt is a system to describe, run, and analyze integration tests
Author: James Connolly <james@silogy.io>
Author-email: James Connolly <james@silogy.io>
Requires-Python: >=3.8
